kr_sentence/__init__.py
kr_sentence/tokenizer.py
kr_sentence-0.0.3.dist-info/LICENSE.txt
kr_sentence-0.0.3.dist-info/METADATA
kr_sentence-0.0.3.dist-info/WHEEL
kr_sentence-0.0.3.dist-info/top_level.txt
kr_sentence-0.0.3.dist-info/RECORD
