Metadata-Version: 2.1
Name: kr-sentence
Version: 0.0.3
Summary: Light-weight sentence tokenizer for Korean.
Home-page: https://github.com/Rairye/kr-sentence
Author: Rairye
License: apache-2.0
Download-URL: https://github.com/Rairye/kr-sentence/archive/refs/tags/v0.0.3.tar.gz
Keywords: Korean,Sentence,Tokenizer
Platform: UNKNOWN
Classifier: Development Status :: 3 - Alpha
Classifier: Intended Audience :: End Users/Desktop
Classifier: Intended Audience :: Developers
Classifier: License :: OSI Approved :: Apache Software License
Classifier: Programming Language :: Python :: 3
Classifier: Programming Language :: Python :: 3.1
Classifier: Programming Language :: Python :: 3.2
Classifier: Programming Language :: Python :: 3.3
Classifier: Programming Language :: Python :: 3.4
Classifier: Programming Language :: Python :: 3.5
Classifier: Programming Language :: Python :: 3.6
Classifier: Programming Language :: Python :: 3.7
License-File: LICENSE.txt
